protobuf_bytes
