Metadata-Version: 2.1
Name: protobuf-bytes
Version: 1.0.0
Summary: Python implementation of protobuf_bytes
Home-page: https://github.com/chokobole/protobuf_bytes
Author: Wonyong Kim
Author-email: chokobole33@gmail.com
License: BSD-3-Clause
Platform: UNKNOWN
Classifier: Programming Language :: Python
Classifier: Programming Language :: Python :: 3
Classifier: Programming Language :: Python :: 3.5
Classifier: Programming Language :: Python :: 3.6
Classifier: Programming Language :: Python :: 3.7
Classifier: Intended Audience :: Developers
Classifier: License :: OSI Approved :: BSD License
Classifier: Topic :: Software Development :: Libraries :: Python Modules
Classifier: Operating System :: OS Independent
